[
  {
    "uuid": "ce4bf7b0d2e917530be76629f645f6fea75edb33",
    "url": "https://www.aljazeera.com/gallery/2024/1/20/refuse-to-fight-jewish-arab-activists-call-for-peace-in-israels-haif",
    "ord_in_thread": 0,
    "parent_url": null,
    "author": "Al Jazeera",
    "published": "2024-01-20T00:00:00Z",
    "title": "‘Refuse to fight’: Jewish, Arab activists call for peace in Israel’s Haifa | Israel War on Gaza News | Al Jazeera",
    "text": "In Pictures ‘Refuse to fight’: Jewish, Arab activists call for peace in Israel’s Haifa Israeli Jews and Palestinian Israelis come together to demand an end to the war on Gaza. Peace activists have taken part in a protest in Israel’s third-largest city, Haifa, demanding a ceasefire in the war on Gaza and the exchange of captives and prisoners between Hamas and Israel. “This is the first time we are seeing this protest happen in the north,” said Al Jazeera’s Stefanie Dekker, reporting from Haifa on Saturday. “It’s a protest with Israeli Jews and Palestinian Israelis, and it is significant because of the two coming together. “The message here is to end the war and that they can only live peacefully side by side with a political solution for the Palestinians,” she said. Omri Evron, a member of the Communist Party of Israel, who helped organise the anti-war protest, spoke to Al Jazeera about the message the protesters were hoping to convey. “The killing of thousands and thousands of Palestinians, the vast majority of whom are innocent civilians, is not only reprehensible, it does not serve the security of the people of Israel. It does not bring us security, it only ensures the next massacre, the next cycle of violence,” he said. “Currently, they [the protestors] are chanting “refuse to kill, refuse to fight, refuse to murder” – this is our call.” Evron admitted there were difficulties in organising a protest of this kind. “It has been difficult, not because there aren’t Jews and Arabs who want to come together who believe in a joint future of peace and equality and national liberation of both people in two states,” he explained. “It has been difficult because the government and the police in particular have done everything in their power to prevent us from coming together, to prevent us from voicing a lawful and peaceful voice. We had to appeal to the Supreme Court of Justice just to allow us to come together and demonstrate.” Al Jazeera’s Dekker said the protesters were not allowed to march, and officials said the protest could not be held at night. But several hundred people were finally able to gather for two hours during the day.",
    "highlightText": "",
    "highlightTitle": "",
    "highlightThreadTitle": "",
    "language": "english",
    "sentiment": "positive",
    "categories": [
      "Politics",
      "War, Conflict and Unrest",
      "Human Interest"
    ],
    "external_links": [],
    "external_images": [],
    "entities": {
      "persons": [
        {
          "name": "arab",
          "sentiment": "neutral"
        },
        {
          "name": "omri evron",
          "sentiment": "none"
        },
        {
          "name": "stefanie dekker",
          "sentiment": "none"
        }
      ],
      "organizations": [
        {
          "name": "gaza news | al jazeera in pictures",
          "sentiment": "neutral"
        },
        {
          "name": "hamas",
          "sentiment": "none"
        },
        {
          "name": "communist party of israel",
          "sentiment": "none"
        },
        {
          "name": "al jazeera",
          "sentiment": "none"
        }
      ],
      "locations": [
        {
          "name": "gaza",
          "sentiment": "none"
        },
        {
          "name": "israel",
          "sentiment": "none"
        },
        {
          "name": "haifa",
          "sentiment": "none"
        }
      ]
    },
    "rating": null,
    "crawled": "2024-01-20T19:45:16.395+02:00",
    "updated": "2024-01-21T00:49:01.133+02:00"
  },
  {
    "uuid": "a56b97a2d57d8027ffea1545df6b3d0d4a67bc8f",
    "url": "https://wlos.com/news/local/trout-creek-campground-glenville-severe-storm-damage-jackson-county-western-north-carolina",
    "ord_in_thread": 0,
    "parent_url": null,
    "author": "Rex Hodge",
    "published": "2024-05-09T23:44:00Z",
    "title": "chevron-right",
    "text": "JACKSON COUNTY, N.C. (WLOS) — A Jackson County campground saw big impacts from a powerful overnight storm. Residents believe it could have been a tornado. The white pines at the Trout Creek Campground near Glenville have very shallow root systems. Given high wind and some saturated ground, they can fall. That's what happened shortly after midnight, very early Thursday morning. When they fell, they didn’t, however, take direct hits on the campers. It was a close call though, and very fortunate since there were people inside them at the time. “Never seen anything like this before,” says Darryl Wiggins. He and his wife, Elaine, have been coming to the mountain campground for four years now, escaping the South Georgia heat. They didn't expect the severity of the overnight weather full of thunder and lightning. [GALLERY: CLEANUP UNDERWAY IN BARNARDSVILLE AFTER EXTENSIVE HAIL DAMAGE](https://wlos.com/news/local/barnardsville-hail-damage-extensive-cleanup-underway-buncombe-county-severe-weather-storm-western-north-carolina-gallery-photos) “The twirling wind and then trees started falling,” Darryl says. “We heard a crash,” says Elaine. “This one fell right across the back of our camper, but it didn't damage the main part of the camper, just tore the luggage rack off the back of it,” says Darryl. “And put a hole in our awning,” says his wife. Their son was busy Thursday morning chain sawing the debris away. They’re all thankful no one was hurt and consider themselves lucky. The Wiggins believe it was a tornado. “I would say it was,” says Elaine. “I would say it was and probably didn't come as low. You’ll see a lot of trees down there where the tops are snapped out, and that’s the reason I think it’s mainly a tornado,” says Darryl. One of the six trees that fell barely missed another camper. The resident wasn’t there at the time. The tree smashed the windshield of his vehicle. Jackson County EMS officials were on site Thursday to help assess the severity of the storm. Official word whether this was a tornado will come from the National Weather Service. “They will send a survey crew out and check the area. But from what we're seeing it does look like maybe an EF-0 tornado has hit in this area,” says Jackson County EMS Director Todd Dillard. He says electricity remains out in the area. “Power, phones, there's some broken poles on up the road,” he says, adding it could be later this week before it’s back on. [EXTENDED OUTAGES PERSIST AS DUKE ENERGY BATTLES SEVERE STORM AFTERMATH IN WNC](https://wlos.com/news/local/duke-energy-restore-electricity-power-severe-storms-hit-western-north-carolina-may-8-hail-wind-thunderstorms-damage-trees-down-flooding) Nearby homes were damaged by the swirling wind. “Sounded like a tunnel... a wind tunnel. I just heard a lot of snapping around us. That's when we started getting real worried,” says Louie Colon. He and his wife took cover between their bathroom and their bedroom and survived. He has a generator to keep the power on and gives a nod to their faith. “Lord had his hand on all this,” says Colon. The Wiggins are also grateful. “We are very thankful,” Elaine says.",
    "highlightText": "",
    "highlightTitle": "",
    "highlightThreadTitle": "",
    "language": "english",
    "sentiment": "negative",
    "categories": [
      "Weather"
    ],
    "webz_reporter": false,
    "external_links": [],
    "external_images": [],
    "entities": {
      "persons": [
        {
          "name": "jackson",
          "sentiment": "negative"
        },
        {
          "name": "darryl wiggins",
          "sentiment": "none"
        },
        {
          "name": "elaine",
          "sentiment": "none"
        }
      ],
      "organizations": [],
      "locations": [
        {
          "name": "jackson county",
          "sentiment": "none"
        },
        {
          "name": "n.c.",
          "sentiment": "none"
        },
        {
          "name": "glenville",
          "sentiment": "none"
        },
        {
          "name": "trout creek campground",
          "sentiment": "none"
        },
        {
          "name": "barnardsville",
          "sentiment": "none"
        },
        {
          "name": "south georgia",
          "sentiment": "none"
        }
      ]
    },
    "rating": null,
    "crawled": "2024-05-10T06:06:02.361+03:00",
    "updated": "2024-05-10T06:06:02.361+03:00"
  },
  {
    "uuid": "8aded2aace832dcd7e817a47f44fbda4c9558a3f",
    "url": "https://www.yucatan.com.mx/espectaculos/2025/02/20/amigo-de-daniel-bisogno-pide-oraciones-confirma-gravedad-de-su-salud.html",
    "ord_in_thread": 0,
    "parent_url": null,
    "author": "Sofía Loyo",
    "published": "2025-02-21T00:26:00Z",
    "title": "Amigo de Daniel Bisogno pide oraciones; confirma gravedad de su salud",
    "text": "Daniel Bisogno y su estado de salud sigue siendo delicado . El conductor se encuentra hospitalizado y en terapia intensiva tras sufrir una falla multiorgánica por una infección en las vías biliares.\n“El Muñeco” fue sometido a un trasplante de hígado el pasado mes de septiembre, sin embargo, tras lo complicado de su situación clínica, se ha rumorado que ahora sufriría otro trasplante de hígado y de los riñones.\nHace unos días se vio a los conductores de Ventaneando acudir al hospital en el que se encuentra, lo que ha despertado las alarmas sobre su salud. Ahora, ha sido un amigo de Daniel Bisogno quien pidió oraciones para el también actor.\nDaniel Bisogno necesita oraciones, confirma amigo del conductor Alex Gou , productor y amigo de Daniel Bisogno dijo ante los medios de comunicación que está preocupado por la crisis de salud a la que nuevamente se enfrenta el presentador, además, confesó que el panorama es complicado y pidió al público oraciones para él, pues lo considera uno de sus mejores amigos y una excelente persona.\n“Es de mis mejores amigos. Está grave, pero estable. Lo único que le deseo a Daniel son todos los rezos. Todo el amor que nos ha dado. Ha sido una excelente persona. Que Diosito decida lo que tenga que decidir”\nDurante la conversación, el productor de teatro confesó que no ha tenido contacto con Daniel Bisogno desde hace dos semanas. Al preguntarle el motivo, simplemente reveló que no se lo permitían.\n“No, no me dejan (visitarlo). Hablé con él hace cómo unos 15 días, pero recemos por nuestro Dani” , apuntó, sin decir más sobre el asunto.\nCabe destacar que algunos miembros de Ventaneando como la conductora Mónica Castañeda , Pedro Sola, y la productora Iyari González sí han visitado a Daniel en el hospital.\n🚨 ÚLTIMA HORA: Daniel Bisogno, en estado crítico, estaría recibiendo esta semana un segundo trasplante de hígado y otro de riñones. 😔\nSegún información de Kadri, el Comité de Trasplantes del Hospital Ángeles aprobó la cirugía.\n¿Cómo consiguieron dos órganos tan rápido?… pic.twitter.com/mDuaILGqjL\n— La Tía Sandra (@TuTiaSandra) February 19, 2025 ¿Cuál es el estado de salud de Daniel Bisogno? De acuerdo con información de Kadri Paparazzi , Daniel Bisogno necesitaría nuevos trasplantes de hígados y riñones , pues los suyos ya no funcionan debido a la falla multiorgánica que sufrió hace unos días.\nRumores indican que los especialistas y médicos han evaluado la situación, y considerarían de nuevo este procedimiento pese a que hace apenas seis meses tuvo el trasplante de hígado.\nDaniel se habría sometido a diversos estudios, incluyendo un ecocardiograma y seis valoraciones médicas, para autorizar los trasplantes, y supuestamente los nuevos órganos llegarían este fin de semana . Mientras tanto, el conductor de Ventaneando continúa en terapia intensiva y bajo tratamiento de hemodiálisis para mantenerlo estable.\nVeo que hay muchas dudas acerca del trasplante hepatico de Daniel Bisogno.\nYo no soy su médico, pero si hubo inmediatez en su caso y habiendo una lista de espera de más de 200 pacientes, lo más seguro es que su trasplante fue de un DONADOR VIVO.\nDe hecho, aquí hay datos de… pic.twitter.com/csefb71PZG\n— Mr Doctor (@MrDoctorOficial) February 20, 2025",
    "highlightText": "",
    "highlightTitle": "",
    "highlightThreadTitle": "",
    "language": "spanish",
    "sentiment": "negative",
    "categories": [
      "Health",
      "Human Interest"
    ],
    "topics": [
      "Health->hospital",
      "Health->medical condition",
      "Health->therapy",
      "Human Interest->funeral and memorial service"
    ],
    "ai_allow": true,
    "has_canonical": false,
    "breaking": true,
    "webz_reporter": false,
    "external_links": [],
    "external_images": [],
    "entities": {
      "persons": [],
      "organizations": [],
      "locations": []
    },
    "syndication": {
      "syndicated": null,
      "syndicate_id": null,
      "first_syndicated": false
    },
    "trust": null,
    "rating": null,
    "crawled": "2025-02-21T02:39:12.957+02:00",
    "updated": "2025-02-21T04:05:07.030+02:00"
  },
  {
    "uuid": "0156dad7cc09327095985a26b9564265b559e814",
    "url": "https://www.nmas.com.mx/estados/imagenes-aurora-boreal-mexico-2024-asi-se-vio-en-tijuana-fotos",
    "ord_in_thread": 0,
    "parent_url": null,
    "author": "@nmas",
    "published": "2024-10-11T13:18:00Z",
    "title": "Imágenes Aurora Boreal México 2024: Así Se Vio en Tijuana Fotos",
    "text": "Aurora Boreal se Vio desde México: Así la Fotografiaron en Tijuana El fenómeno se debió a una tormenta solar que llegó al ambiente terrestre desde el jueves 10 de octubre N+ COMPARTE: La noche del 10 de octubre de 2024, una impactante aurora boreal causada por una tormenta solar sorprendió a pobladores del norte de México, quienes pudieron admirarla, fotografiarla y compartir diversas imágenes a través de [redes sociales](https://www.nmas.com.mx/temas/redes-sociales/). Según información del Laboratorio Nacional de Clima Espacial (LANCE), del Instituto de Geofísica de la Universidad Nacional Autónoma de México ([UNAM](https://www.nmas.com.mx/temas/unam/)), la tormenta solar se detectó desde la noche del martes pasado y llegó al ambiente terrestre a las 09:00 horas de ayer. Incluso, el LANCE previó que el tránsito de la tormenta se extienda hasta la mañana de este viernes. Noticia relacionada: [Sorprende Aurora Boreal a Habitantes en Nuevo León](https://www.nmas.com.mx/monterrey/sorprende-aurora-boreal-a-habitantes-en-nuevo-leon/) Fotografían aurora boreal desde Tijuana En redes sociales, usuarios compartieron imágenes de la aurora boreal vista desde Tijuana, Baja California. La cuenta de Facebook Astrofotógrafos de Baja California expresó que el poder observar la aurora boreal en la entidad es increíble debido a la latitud del estado, y destacó que ésta se debió la tormenta geomagnética. En las fotos, captadas por Jonathan Cazares, se observó en el cielo los colores de la aurora, entre rosas y morados. Auroras polares De acuerdo con información de Héctor Javier Durand Manterola, experto de la UNAM, las auroras polares son fenómenos luminosos de la alta atmósfera que ocurren por la entrada de partículas de viento solar por las líneas del campo magnético terrestre. Eso ocasiona estimulación en átomos y moléculas del aire, lo que produce luz durante el proceso. Además, el color de la luz que se observa depende del tipo de las partículas que son estimuladas y de su altitud. Así, se observan los colores verde y rojo cuando se trata de oxígeno; rosa para nitrógeno y azul-morado para hidrógeno y helio. Se les llama auroras polares porque generalmente ocurren cerca de los polos magnéticos de la Tierra; a las que ocurren en los alrededores del polo norte se les llama “auroras boreales” y a las que ocurren cerca del polo sur se les conoce como “auroras australes”. Aurora polar vista desde el espacio exterior Cabe señalar que apenas hace unos días, el piloto y astronauta Matthew Dominick compartió una impresionante imagen de una aurora roja y verde captada desde el Dragon Endeavour, acoplado al frente de la Estación Espacial Internacional. Peering out a Dragon Endeavor window that frames red and green aurora streaming by Dragon Freedom docked to the front of the International Space Station. — Matthew Dominick (@dominickmatthew) When Crew-9 arrived I moved out of my crew quarters on the ISS to make room for[@AstroHague]. I now sleep in Dragon Endeavor…[pic.twitter.com/34XfeLXpcH][October 7, 2024] Tormenta solar Sobre la tormenta solar, el LANCE de la UNAM advirtió en un comunicado que entre ayer y hoy podrían ocurrir en el planeta alteraciones tecnológicas como daños en telecomunicaciones, sistemas de posicionamiento global (GPS), radiocomunicaciones y sistemas de distribución de energía y de navegación debido a la tormenta solar. Dijo que desde que se identificó, este evento se catalogó como riesgo potencial para el clima espacial terrestre, debido a que sus características hacen posible que provoque actividad geomagnética intensa o severa (G3 o G4) y perturbaciones ionosféricas significativas. Según el LANCE, “las tormentas geomagnéticas son alteraciones a nivel planetario del campo magnético terrestre, y las perturbaciones ionosféricas son alteraciones de la composición de la capa externa de la atmósfera de la Tierra”. Destacó que estos fenómenos no impactan directamente a la salud humana, pero pueden causar afectaciones en tecnologías. ☀️🌇 La tormenta solar, ocurrida el 8 de octubre, de considerable magnitud ha alcanzado la Tierra, lo que ha generado preocupación por sus posibles efectos sobre la infraestructura tecnológica global. El — UNAM Global (@unamglobal)[#ExpertoUNAM]Pedro Corona explica. ⬇️[https://t.co/PaNCrLkf7U][October 11, 2024] Historias recomendadas: [Tesla Presenta Taxi Sin Conductor y Promete Revolucionar el Transporte de Personas](https://www.nmas.com.mx/tecnologia/tesla-presenta-taxi-sin-conductor-y-promete-revolucionar-el-transporte-de-personas/)[Organización Japonesa Nihon Hidankyo Ganadora del Premio Nobel de la Paz 2024](https://www.nmas.com.mx/internacional/europa/organizacion-japonesa-nihon-hidankyo-ganadora-del-premio-nobel-de-la-paz-2024/)[Sobreviven en una Isla al Norte de Yucatán en Medio del Paso del Huracán 'Milton'](https://www.nmas.com.mx/estados/sobreviven-en-una-isla-al-norte-de-yucatan-en-medio-del-paso-del-huracan-milton/) Con información de N+. spb",
    "highlightText": "",
    "highlightTitle": "",
    "highlightThreadTitle": "",
    "language": "spanish",
    "sentiment": "positive",
    "categories": [
      "Weather"
    ],
    "ai_allow": true,
    "webz_reporter": false,
    "external_links": [
      "https://t.co/PaNCrLkf7U",
      "https://www.t.co/PaNCrLkf7U"
    ],
    "external_images": [],
    "entities": {
      "persons": [],
      "organizations": [],
      "locations": []
    },
    "syndication": {
      "syndicated": null,
      "syndicate_id": null,
      "first_syndicated": false
    },
    "rating": null,
    "crawled": "2024-10-11T16:54:04.381+03:00",
    "updated": "2024-10-11T16:54:04.381+03:00"
  },
  {
    "uuid": "6fd843c48b74eddaa4561c7d91c754786ce21fcd",
    "url": "http://business.bigspringherald.com/bigspringherald/article/getnews-2024-4-4-astir-home-health-care-reinforces-its-dedication-to-premier-home-health-care-in-bloomfield-nj",
    "ord_in_thread": 0,
    "parent_url": null,
    "author": "Get News",
    "published": "2024-04-04T00:00:00Z",
    "title": "Astir Home Health Care Reinforces Its Dedication to Premier Home Health Care in Bloomfield, NJ | User | bigspringherald.com",
    "text": "Astir Home Health Care in Bloomfield, NJ, pledges to continue providing exceptional home health care, emphasizing personalized plans and the well-being of each client. Their dedicated team offers comprehensive services to ensure seniors live comfortably and with dignity at home. For more details, visit https://astirhc.com Bloomfield, NJ - Astir Home Health Care, a leading provider of home health care services, today announced its unwavering commitment to continue offering superior home health care in Bloomfield, NJ. Recognized for its dedication to quality and compassionate care, Astir Home Health Care ensures that families seeking home care in Bloomfield for their loved ones can access the support they need to live comfortably and with dignity in their homes. This ongoing service reflects the company's response to the growing demand for reliable, high-quality home care solutions in the region, emphasizing the importance of personalized care plans and the well-being of each individual.\n“At Astir Home Health Care, we are deeply committed to the Bloomfield community. Our focus on providing exceptional home health care services is about more than just meeting the basic needs of our clients; it's about enriching their lives and offering peace of mind to their families,” said Cynthia Palmer, owner of Astir Home Health Care. “Our dedication to this mission is stronger than ever as we continue to adapt to the evolving needs of our community, ensuring that every individual and family we serve receives the personalized, compassionate care they deserve.”\nAstir Home Health Care's approach to home health care is tailored to meet each client's unique needs, ranging from daily living assistance to more complex health care requirements. This personalized approach ensures that every client enjoys a higher quality of life, with services designed to foster independence, provide comfort, and enhance overall well-being.\nFamilies in Bloomfield, NJ, looking for top-tier home health care services can rely on Astir Home Health Care for their loved ones' needs.\nFor more information about Astir Home Health Care and their home health care in Bloomfield, NJ , please visit their website at https://astirhc.com\nAbout Astir Home Health Care:\nAstir Home Health Care is a premier provider of home health care services in Bloomfield, NJ. With a reputation for excellence and a team of dedicated health care professionals, Astir Home Health Care offers a comprehensive range of services designed to meet the diverse needs of the elderly community. Committed to enhancing the lives of seniors and their families, Astir Home Health Care remains a leading choice for those seeking quality, compassionate care in the comfort of their own homes.\nMedia Contact\nCompany Name: Astir Home Health Care\nContact Person: Cynthia Palmer\nEmail: Send Email\nPhone: +1 973 259 1000\nAddress: 192 Broad St\nCity: Bloomfield\nState: NJ\nCountry: United States\nWebsite: https://astirhc.com/\nData & News supplied by www.cloudquote.io\nStock quotes supplied by Barchart\nQuotes delayed at least 20 minutes.\nBy accessing this page, you agree to the following\nPrivacy Policy and Terms and Conditions .",
    "highlightText": "",
    "highlightTitle": "",
    "highlightThreadTitle": "",
    "language": "english",
    "sentiment": "positive",
    "categories": [
      "Human Interest",
      "Health"
    ],
    "external_links": [
      "https://tracking.newsrpm.com/pixel?slug=getnews-2024-4-4-astir-home-health-care-reinforces-its-dedication-to-premier-home-health-care-in-bloomfield-nj",
      "https://www.getnews.info/press_stat.php?pr=astir-home-health-care-reinforces-its-dedication-to-premier-home-health-care-in-bloomfield-nj",
      "http://www.universalpressrelease.com/?pr=astir-home-health-care-reinforces-its-dedication-to-premier-home-health-care-in-bloomfield-nj",
      "https://astirhc.com",
      "https://www.cloudquote.io",
      "https://www.googletagmanager.com/gtag/js?id=UA-8590502-3",
      "https://astirhc.com/",
      "https://www.cloudquote.io/article/5",
      "https://www.cloudquote.io/article/6",
      "https://astirhc.com/location-home-care-in-bloomfield-nj/",
      "https://www.googletagmanager.com/gtag/js",
      "https://cloudquote.io/article/5",
      "https://cloudquote.io/article/6",
      "https://www.astirhc.com",
      "https://getnews.info/press_stat.php?pr=astir-home-health-care-reinforces-its-dedication-to-premier-home-health-care-in-bloomfield-nj",
      "https://tracking.newsrpm.com/pixel",
      "https://astirhc.com",
      "https://googletagmanager.com/gtag/js?id=UA-8590502-3",
      "https://www.astirhc.com/",
      "https://www.getnews.info/press_stat.php",
      "http://www.universalpressrelease.com/",
      "https://cloudquote.io",
      "https://astirhc.com/location-home-care-in-bloomfield-nj",
      "https://www.astirhc.com/location-home-care-in-bloomfield-nj/",
      "http://universalpressrelease.com/?pr=astir-home-health-care-reinforces-its-dedication-to-premier-home-health-care-in-bloomfield-nj",
      "https://www.tracking.newsrpm.com/pixel?slug=getnews-2024-4-4-astir-home-health-care-reinforces-its-dedication-to-premier-home-health-care-in-bloomfield-nj"
    ],
    "external_images": [],
    "entities": {
      "persons": [],
      "organizations": [
        {
          "name": "premier home health care",
          "sentiment": "negative"
        },
        {
          "name": "astir home health care",
          "sentiment": "negative"
        },
        {
          "name": "nj - astir home health care",
          "sentiment": "none"
        }
      ],
      "locations": [
        {
          "name": "bloomfield",
          "sentiment": "none"
        }
      ]
    },
    "rating": null,
    "crawled": "2024-04-05T01:42:38.477+03:00",
    "updated": "2024-04-05T01:42:38.477+03:00"
  },
  {
    "uuid": "9a00cfd38412da13132a261614ac96e6d4538b20",
    "url": "https://mynorthwest.com/3944602/killer-whale-calf-spotted-second-may-come-soon/",
    "ord_in_thread": 0,
    "parent_url": null,
    "author": "KIRO Newsradio staff",
    "published": "2023-12-29T00:35:00Z",
    "title": "Newborn orca whale calf spotted, second may be coming soon",
    "text": "Newborn orca whale calf spotted, second may be coming soon\nDec 28, 2023, 4:35 PM\n(Photo courtesy of Maya Sears, NMFS Permit 27052, via the Center for Whale Research)\nA new member of the endangered Southern Resident killer whale (orca) population has been spotted around Puget Sound, and a second may be on the way, researchers said.\nThe Center for Whale Research confirmed on its social media channels and on its website this week a new calf was spotted with the J pod on Tuesday swimming close to female whale J-40.\n“It’s great! It’s always fun to have a new one,” said Dave Ellifrit, the orca survey lead with the center.\nPuget Sound killer whale researchers Maya and Mark Sears reported the appearance and snapped photos of the calf. It is believed the whale is just a few days old and it is not yet known if it’s a boy or a girl.\nMore on orcas in WA:\nYoung orca calf spotted with pod of Southern Resident killer whales\n“I guess they had been out on (Dec. 23) and the calf wasn’t there so it’s very young. A couple of days old,” Ellifrit said.\nThe calf is sticking closely to the 19-year-old female whale J-40, so she’s likely its mother. Ellifrit pointed out that J-40’s calf is her first known baby.\n“From the pictures I’ve seen, it looks like a healthy little calf. When they’re that young they’re always kind of lumpy and bumpy. They’ll fill out over the next few weeks,” Ellifrit noted.\nAn unexpected birth, with another possibly coming\nEllifrit said the birth of the calf was a bit of a surprise.\n“She wasn’t a whale that we were expecting to have a calf because she didn’t look noticeably pregnant the last time we got (a look at) the whales from the air, this fall.”\nIn fact, whale watchers had been keeping an eye on a different female.\n“J-46 — who’s a few years younger — is the whale we were expecting to have a calf this winter,” Ellifrit said. “She was looking pretty pregnant in mid-October, so if we’re lucky we might have a two-J-pod-calf winter.”\nTwo calves born in L pod during the summer\nThe center confirmed in July L pod members L-119 and L-94\neach gave birth to a calf. At the time, the two calves were “very active and social” and neither showed any immediate signs of illness or abnormality.\nWhale of a report:\n2 new orca calves spotted in L pod\nL-119’s calf is named L-126 and L-94’s is L-127. L-126 is L-119’s first calf, while L127 is L94’s third.\n“I mean, every single addition we can get to this population is huge,” Michael Weiss, the center’s research director said to KIRO Newsradio in July.\nThese were the first calves born in L pod since 2021. These are also the first calves born in the L12 subgroup since 2018.\nThat’s still only three — with a possible fourth calf — born in one year to the endangered group.\n“The whales who should be having calves aren’t having them as often as a population that you would expect is well fed,” he says.\nSurvivorship from the last baby boom in 2015 wasn’t quite what researchers had hoped for, Brad Hanson, wildlife biologist for the\nNational Oceanic and Atmospheric Administration (NOAA), said to The Seattle Times this week.\n“It’s really, really good news,” Hanson\nsaid of the new calf. “It also comes with the trepidation of how they’re going to fare throughout the first few years of their life.”\nMore orca information\nUnlike transient or “Bigg’s” killer whales that dine on a variety of marine mammals, Southern Resident killer whales eat Chinook salmon almost exclusively, a fish whose numbers are also dwindling.\nThe whales may also be expanding the area they travel in the search for food. Researchers who monitor the endangered whales say the animals travel a wide range, with some spotted from southeast Alaska to Monterey Bay, California.\n“They have a huge, huge area that they cover over the course of a year,” Weiss said.\nHow did Tokitae die?\nNecropsy findings for beloved whale released\nResearchers say underwater noise from vessels interferes with feeding, and pollution also takes a toll on the endangered whale population.\nThere are an estimated 75 Southern Residents killer whales, down from 98 in 1995.\nHeather Bosch is an award-winning anchor and reporter on KIRO Newsradio. You can read more of her stories\nhere. Follow Heather X, formerly known as Twitter or .\nSteve Coogan is the lead editor at MyNorthwest.\nContributing: Lisa Brooks, KIRO Newsradio",
    "highlightText": "",
    "highlightTitle": "",
    "highlightThreadTitle": "",
    "language": "english",
    "sentiment": "positive",
    "categories": [
      "Science and Technology",
      "Environment",
      "Human Interest"
    ],
    "external_links": [
      "https://twitter.com/HeatherBosch",
      "https://www.whaleresearch.com/",
      "https://www.seattletimes.com/seattle-news/environment/newborn-southern-resident-orca-spotted-in-puget-sound/",
      "https://www.instagram.com/p/C1YCOawh4xp/?img_index=1",
      "https://www.facebook.com/CenterForWhaleResearch/posts/pfbid02K4paChfsTVnozXsLBAikr8fh1YGdBhPbP6URUpaxye8C1gyXNu7niugKno8NgEoLl",
      "https://www.noaa.gov/",
      "https://www.whaleresearch.com",
      "https://noaa.gov/",
      "https://facebook.com/CenterForWhaleResearch/posts/pfbid02K4paChfsTVnozXsLBAikr8fh1YGdBhPbP6URUpaxye8C1gyXNu7niugKno8NgEoLl",
      "https://www.noaa.gov",
      "https://instagram.com/p/C1YCOawh4xp/?img_index=1",
      "https://www.seattletimes.com/seattle-news/environment/newborn-southern-resident-orca-spotted-in-puget-sound",
      "https://seattletimes.com/seattle-news/environment/newborn-southern-resident-orca-spotted-in-puget-sound/",
      "https://whaleresearch.com/",
      "https://www.instagram.com/p/C1YCOawh4xp/",
      "https://www.twitter.com/HeatherBosch"
    ],
    "external_images": [],
    "entities": {
      "persons": [
        {
          "name": "maya sears",
          "sentiment": "none"
        },
        {
          "name": "maya",
          "sentiment": "none"
        },
        {
          "name": "dave ellifrit",
          "sentiment": "none"
        },
        {
          "name": "mark sears",
          "sentiment": "none"
        },
        {
          "name": "ellifrit",
          "sentiment": "none"
        }
      ],
      "organizations": [
        {
          "name": "center for whale research",
          "sentiment": "none"
        },
        {
          "name": "nmfs",
          "sentiment": "none"
        }
      ],
      "locations": [
        {
          "name": "wa",
          "sentiment": "none"
        },
        {
          "name": "puget sound",
          "sentiment": "none"
        }
      ]
    },
    "rating": null,
    "crawled": "2023-12-29T03:12:05.458+02:00",
    "updated": "2023-12-29T03:12:05.458+02:00"
  },
  {
    "uuid": "d7d3ae556718843770af5127441a44ac96aa723f",
    "url": "https://www.jdsupra.com/legalnews/year-in-review-top-deals-in-2023-7817564/",
    "ord_in_thread": 0,
    "parent_url": null,
    "author": "Goodwin",
    "published": "2023-12-28T23:15:00Z",
    "title": "Year in Review: Top Deals in 2023",
    "text": "According to PWC, “2023 was a reasonably strong year for the pharmaceutical and life sciences sector with both deal value and volume of M&A close to pre-pandemic levels.” Below is a recap of the top M&A deals in 2023 that focus on biologics and biosimilars and were covered on the Big Molecule Watch. In March, Coya Therapeutics, Inc. (“Coya”), a biopharmaceutical company based in Houston, announced a worldwide agreement with Dr. Reddy’s Laboratories Ltd. (“Dr. Reddy’s”) to license Dr. Reddy’s proposed biosimilar abatacept for the development and commercialization of COYA 302 for the treatment of neurodegenerative conditions. Under the agreement, Coya in-licensed Dr. Reddy’s proposed abatacept biosimilar and obtained exclusive rights to develop and commercialize COYA 302 across multiple neurodegenerative diseases in multiple territories, including in North and South America, the EU, United Kingdom, and Japan. Dr. Reddy’s will have exclusive rights to the same in areas outside of these territories. Coya later reported its 48-week clinical data for a proof-of-concept open-label study in 4 patients with amyotrophic lateral sclerosis (ALS) demonstrating that treatment with COYA 302 appeared to ameliorate disease progression. In October, Coya reported new data supporting the mechanism of action of COYA 302 for the treatment of Amyotrophic Lateral Sclerosis (“ALS”) at the 22nd Annual Northeast ALS Consortium Meeting. In September, Meitheal, a biopharmaceutical company based in Chicago, entered into an exclusive licensing deal with Tonghua Dongbao Pharmaceutical Co., Ltd. (“THDB”) to market three biosimilars of the top selling branded insulins in the United States – asprat, lispro and glargine. All are expected to begin clinical trials in 2024. The agreement granted Meitheal and its parent company, Nanjing King-Friend Biochemical Pharmaceutical Co., Ltd. (“NKF”), exclusive rights to commercialize the three biosimilar insulin products upon approval by the FDA, estimated to be on or around 2026. THDB and NKF will jointly handle product development and supply. In January, Coherus BioSciences, Inc. (“Coherus”) announced the execution of a binding term sheet with Klinge Biopharma GmbH (“Klinge Biopharma”) for the exclusive commercialization rights to FYB203, Formycon AG’s (“Formycon”) biosimilar candidate to EYLEA (aflibercept), in the United States. Under the binding term sheet, Coherus will make a total upfront payment to Klinge of approximately €30 million, comprised of cash and Coherus common stock, thirty days after the execution of the definitive agreements. Coherus will also make other regulatory and launch milestone payments and share profits approximately equally with Klinge in consideration for the commercialization rights to FYB203 in the United States. Formycon AG is entitled to participate in all Klinge income under the agreement with Coherus in the mid-single to low-double-digit-percentage range. Coherus intends to launch the product at EYLEA biosimilar market formation, currently expected to be in 2025, if approved. In January, Alteogen, Inc. (“Alteogen”) announced that it entered an exclusive license agreement with Sandoz AG (“Sandoz”) pursuant to which Sandoz will have worldwide rights to use Alteogen’s ALT-B4 hyaluronidase, derived using HYBROZYME Technology, to develop and commercialize a subcutaneous version of a Sandoz biosimilar product. Sandoz also has an option to license the HYBROZYME Technology for two other products. Under the agreement, Alteogen received an upfront payment and is eligible to receive milestone payments upon Sandoz’ achievement of specified development, regulatory and sales milestones. Alteogen will be entitled to receive tiered royalties ranging from mid-single digit to low-double digit on sales of the commercialized product. Alteogen will be responsible for regulatory development and commercial supply of ALT-B4 to Sandoz. For the two option products under this agreement, Alteogen and Sandoz will negotiate separate agreements at the time of exercising each option. The agreement allows for both companies to collaborate on the development and commercialization of additional products that Sandoz may undertake to develop. In June, Coherus announced that it has entered into a definitive merger agreement with Surface Oncology, Inc. (“Surface Oncology”), where, at the closing, Coherus will acquire Surface Oncology, a clinical-stage immuno-oncology (“I-O”) company developing next-generation immunotherapies that target the tumor microenvironment. Coherus noted that this acquisition adds two differentiated clinical stage assets to Coherus’ novel I-O pipeline: SRF388, a novel IL-27-targeted antibody currently being evaluated in Phase 2 clinical trials in lung cancer and liver cancer, and SFR114, a CCR8-targeted antibody currently in a Phase 1/2 study as a monotherapy in patients with advanced solid tumors. There was reported a stock for stock transaction valued at up to $65 million and an approximate three-fold premium over Surface’s anticipated net cash of $20 to $25 million at closing. Surface shareholders will also receive CVRs based on potential future payments for previously partnered assets and for potential ex-US licensing. [View source.] See more » DISCLAIMER: Because of the generality of this update, the information provided herein may not be applicable in all situations and should not be acted upon without specific legal advice based on particular situations. © Goodwin Refine your interests »",
    "highlightText": "",
    "highlightTitle": "",
    "highlightThreadTitle": "",
    "language": "english",
    "sentiment": "positive",
    "categories": [
      "Economy, Business and Finance"
    ],
    "external_links": [],
    "external_images": [],
    "entities": {
      "persons": [
        {
          "name": "reddy",
          "sentiment": "none"
        },
        {
          "name": "coya",
          "sentiment": "none"
        }
      ],
      "organizations": [
        {
          "name": "pwc",
          "sentiment": "negative"
        },
        {
          "name": "eu",
          "sentiment": "none"
        },
        {
          "name": "coya therapeutics, inc.",
          "sentiment": "none"
        },
        {
          "name": "’s laboratories ltd.",
          "sentiment": "none"
        }
      ],
      "locations": [
        {
          "name": "south america",
          "sentiment": "none"
        },
        {
          "name": "japan",
          "sentiment": "none"
        },
        {
          "name": "united kingdom",
          "sentiment": "none"
        },
        {
          "name": "north",
          "sentiment": "none"
        },
        {
          "name": "houston",
          "sentiment": "none"
        }
      ]
    },
    "rating": null,
    "crawled": "2023-12-29T01:17:37.736+02:00",
    "updated": "2023-12-29T02:11:58.944+02:00"
  },
  {
    "uuid": "e5da0b2a35239c6add3ff8308ffd76a050659f97",
    "url": "https://www.mapnews.ma/fr/actualites/monde/les-initiatives-de-lagence-bayt-mal-al-qods-acharif-ont-laiss%C3%A9-une-grande-empreinte",
    "ord_in_thread": 0,
    "parent_url": null,
    "author": "admin",
    "published": "2024-09-19T15:22:00Z",
    "title": "Les initiatives de l'Agence Bayt Mal Al-Qods Acharif ont laissé une \"grande empreinte\" dans la Ville Sainte (ministre palestinien)",
    "text": "-\n-\n-\n[ACTIVITÉS ROYALES](/fr/activites_royales)\nActivités RoyalesSa Majesté le Roi Mohammed VI, Amir Al-Mouminine, que Dieu L'assiste, accompagné de SAR le Prince Héritier Moulay El Hassan, de SAR le Prince ...Sa Majesté le Roi Mohammed VI, Amir Al Mouminine, que Dieu L’assiste, a bien voulu accorder Sa Grâce, à l’occasion de l’Aïd Al Mawlid Annabaoui, à ...\n[EN LIRE PLUS](/fr/activites_royales)\nDiscours et messages de SM le Roi\n-\n29 juillet 2024Sa Majesté le Roi Mohammed VI, que Dieu L'assiste, a adressé, lundi, un Discours à Son peuple fidèle à l’occasion du 25ème anniversaire de l’accession du Souverain au Trône de Ses glorieux Ancêtres. ...\n[EN LIRE PLUS](/fr/discours-messages-sm-le-roi)\n-\n[DISCOURS ET MESSAGES DE SM LE ROI](/fr/discours-messages-sm-le-roi)\n-\n[ACTIVITÉS PRINCIÉRES](/fr/activites_princieres)\n-\n[ACTUALITÉS](javascript: void(0);)\n-\n[ACTUALITÉS](javascript: void(0);)\nPolitique\nCulture\nGénéral\nEconomie\n-\nLE PROGRAMME D'AIDE SOCIALE DIRECTE\n-\nFAKE NEWS\n-\n[DOSSIERS](/fr/dossiers)\n-\n[MAP MEDIA](javascript: void(0);)\n-\n[MAROC](javascript: void(0);)\n-\nMAP\n-",
    "highlightText": "",
    "highlightTitle": "",
    "highlightThreadTitle": "",
    "language": "french",
    "sentiment": "positive",
    "categories": [
      "Politics",
      "Social Issue",
      "Human Interest"
    ],
    "ai_allow": true,
    "webz_reporter": false,
    "external_links": [
      "http://www.map.ma",
      "http://map.ma"
    ],
    "external_images": [],
    "entities": {
      "persons": [],
      "organizations": [],
      "locations": []
    },
    "syndication": null,
    "rating": null,
    "crawled": "2024-09-20T00:42:15.539+03:00",
    "updated": "2024-09-20T00:42:15.539+03:00"
  }
]